LICENSE
MANIFEST.in
README.md
python-rpmfluff.spec
setup.py
rpmfluff/__init__.py
rpmfluff/check.py
rpmfluff/make.py
rpmfluff/rpmbuild.py
rpmfluff/samples.py
rpmfluff/sourcefile.py
rpmfluff/subpackage.py
rpmfluff/tarball.py
rpmfluff/test.py
rpmfluff/trigger.py
rpmfluff/utils.py
rpmfluff/yumrepobuild.py
rpmfluff.egg-info/PKG-INFO
rpmfluff.egg-info/SOURCES.txt
rpmfluff.egg-info/dependency_links.txt
rpmfluff.egg-info/top_level.txt