Metadata-Version: 2.4
Name: rpmfluff
Version: 0.6.7
Summary: Lightweight way of building RPMs, and sabotaging them
Home-page: https://pagure.io/rpmfluff
Author: David Malcolm
Author-email: dmalcolm@redhat.com
Maintainer: Jan Hutar
Maintainer-email: jhutar@redhat.com
License: GPL-2.0+
License-File: LICENSE
Dynamic: author
Dynamic: author-email
Dynamic: description
Dynamic: home-page
Dynamic: license
Dynamic: license-file
Dynamic: maintainer
Dynamic: maintainer-email
Dynamic: summary
